tenda4g09/__init__.py
tenda4g09/example.py
tenda4g09-0.1.0.post3.dist-info/LICENSE
tenda4g09-0.1.0.post3.dist-info/METADATA
tenda4g09-0.1.0.post3.dist-info/WHEEL
tenda4g09-0.1.0.post3.dist-info/top_level.txt
tenda4g09-0.1.0.post3.dist-info/RECORD
