Metadata-Version: 2.1
Name: tenda4g09
Version: 0.1.0.post3
Summary: A small library for the Tender 4G09 router
Home-page: https://github.com/dorianim/py-tenda4g09
Author: Dorian Zedler
Author-email: mail@dorian.im
License: UNKNOWN
Project-URL: Bug Tracker, https://github.com/dorianim/py-tenda4g09/issues
Platform: UNKNOWN
Classifier: Programming Language :: Python :: 3
Classifier: License :: OSI Approved :: GNU Affero General Public License v3
Classifier: Operating System :: OS Independent
Requires-Python: >=3.6
License-File: LICENSE
Requires-Dist: requests
